{
    "name": "Spotlights",
    "types": [
        {
            "description": [
                "@example",
                "```json",
                "{",
                "  \"spotlights\": [",
                "    {",
                "      \"end_date\": \"2019-03-22T00:00:00+00:00\",",
                "      \"id\": 1,",
                "      \"mode_specific\": false,",
                "      \"name\": \"Best spinning circles 2019\",",
                "      \"start_date\": \"2019-02-22T00:00:00+00:00\",",
                "      \"type\": \"yearly\",",
                "    },",
                "    {",
                "      \"end_date\": \"2019-03-22T00:00:00+00:00\",",
                "      \"id\": 2,",
                "      \"mode_specific\": true,",
                "      \"name\": \"Ultimate fruit collector February 2019\",",
                "      \"start_date\": \"2019-02-22T00:00:00+00:00\",",
                "      \"type\": \"monthly\",",
                "    }",
                "  ],",
                "}",
                "```"
            ],
            "extendsList": [],
            "name": "Spotlights",
            "properties": [
                {
                    "key": "spotlights",
                    "optional": false,
                    "type": [
                        {
                            "original": "`Spotlight`[]",
                            "array": true,
                            "fixed": "Spotlight"
                        }
                    ],
                    "description": [
                        "An array of spotlights"
                    ]
                }
            ],
            "source": "https://osu.ppy.sh/docs/index.html#spotlights"
        }
    ]
}